README.md
setup.cfg
setup.py
testoy/__init__.py
testoy/build_sort_case.py
testoy/test_sort.py
testoy.egg-info/PKG-INFO
testoy.egg-info/SOURCES.txt
testoy.egg-info/dependency_links.txt
testoy.egg-info/requires.txt
testoy.egg-info/top_level.txt