Metadata-Version: 2.1
Name: testoy
Version: 0.0.1
Summary: Test your code with countless toys!
Home-page: https://github.com/pricelesscode/testoy
Author: Matt Lee
Author-email: poream3387@gmail.com
License: MIT
Platform: UNKNOWN
Classifier: Development Status :: 3 - Alpha
Classifier: Intended Audience :: Developers
Classifier: License :: OSI Approved :: MIT License
Classifier: Programming Language :: Python :: 3
Classifier: Operating System :: OS Independent
Requires-Python: >=3.6.4
